steed/__init__.py
steed/__main__.py
steed-0.2.0.dist-info/METADATA
steed-0.2.0.dist-info/WHEEL
steed-0.2.0.dist-info/entry_points.txt
steed-0.2.0.dist-info/RECORD
